sk_algo_assist/__init__.py
sk_algo_assist/algo_assist.py
sk_algo_assist-1.0.dist-info/METADATA
sk_algo_assist-1.0.dist-info/RECORD
sk_algo_assist-1.0.dist-info/WHEEL
sk_algo_assist-1.0.dist-info/top_level.txt
