Metadata-Version: 2.1
Name: sk-algo-assist
Version: 1.0
Summary: An assistant for algorithm selection to help Data Scientists using SKLearn.
Home-page: https://github.com/GouthamPeri/sk_algo_assist
Author: Goutham Peri
Author-email: sivagoutham369@gmail.com
License: MIT
Platform: UNKNOWN
